curve_curator/__init__.py
curve_curator/__main__.py
curve_curator/dashboard.py
curve_curator/data_parser.py
curve_curator/data_simulator.py
curve_curator/models.py
curve_curator/quality_control.py
curve_curator/quantification.py
curve_curator/search_engine_outputs/DIANN.py
curve_curator/search_engine_outputs/MSFragger.py
curve_curator/search_engine_outputs/MaxQuant.py
curve_curator/search_engine_outputs/ProteomeDiscoverer.py
curve_curator/search_engine_outputs/__init__.py
curve_curator/thresholding.py
curve_curator/toml_parser.py
curve_curator/toolbox.py
curve_curator/user_interface.py
curve_curator-0.6.0.dist-info/LICENSE
curve_curator-0.6.0.dist-info/METADATA
curve_curator-0.6.0.dist-info/WHEEL
curve_curator-0.6.0.dist-info/entry_points.txt
curve_curator-0.6.0.dist-info/RECORD
