Metadata-Version: 2.3
Name: curve_curator
Version: 0.6.0
Summary: CurveCurator is an open-source analysis platform for any dose-dependent data. It fits a classical 4-parameter equation to estimate effect potency, effect size, and the statistical significance of the observed response. 2D-thresholding efficiently reduces false positives in high-throughput experiments and separates relevant from irrelevant or insignificant hits in an automated and unbiased manner. An interactive dashboard allows users to quickly explore data locally.
License: Apache License, Version 2.0
Author: Florian P. Bayer
Author-email: f.bayer@tum.de
Requires-Python: >=3.11,<3.14
Classifier: License :: Other/Proprietary License
Classifier: Programming Language :: Python :: 3
Classifier: Programming Language :: Python :: 3.11
Classifier: Programming Language :: Python :: 3.12
Classifier: Programming Language :: Python :: 3.13
Requires-Dist: bokeh (>=3.4.0,<3.8.0)
Requires-Dist: numpy (>=1.25.0,<3.0)
Requires-Dist: pandas (>=2.1.0,<3.0.0)
Requires-Dist: pytest (>=7.4.3,<8.0.0)
Requires-Dist: scipy (>=1.10.1,<2.0.0)
Requires-Dist: statsmodels (>=0.14.0,<0.15.0)
Requires-Dist: tqdm (>=4.66.1,<5.0.0)
